pysuricata/__init__.py
pysuricata/_version.py
pysuricata/api.py
pysuricata/checkpoint.py
pysuricata/config.py
pysuricata/logger.py
pysuricata/report.py
pysuricata/utils.py
pysuricata/accumulators/__init__.py
pysuricata/accumulators/algorithms.py
pysuricata/accumulators/boolean.py
pysuricata/accumulators/categorical.py
pysuricata/accumulators/config.py
pysuricata/accumulators/datetime.py
pysuricata/accumulators/factory.py
pysuricata/accumulators/numeric.py
pysuricata/accumulators/protocols.py
pysuricata/accumulators/sketches.py
pysuricata/compute/__init__.py
pysuricata/compute/consume.py
pysuricata/compute/consume_polars.py
pysuricata/compute/manifest.py
pysuricata/compute/adapters/__init__.py
pysuricata/compute/adapters/base.py
pysuricata/compute/adapters/pandas.py
pysuricata/compute/adapters/polars.py
pysuricata/compute/analysis/__init__.py
pysuricata/compute/analysis/correlation.py
pysuricata/compute/analysis/estimators.py
pysuricata/compute/analysis/metrics.py
pysuricata/compute/core/__init__.py
pysuricata/compute/core/exceptions.py
pysuricata/compute/core/protocols.py
pysuricata/compute/core/types.py
pysuricata/compute/orchestration/__init__.py
pysuricata/compute/orchestration/engine.py
pysuricata/compute/orchestration/manifest.py
pysuricata/compute/processing/__init__.py
pysuricata/compute/processing/chunking.py
pysuricata/compute/processing/conversion.py
pysuricata/compute/processing/inference.py
pysuricata/io/__init__.py
pysuricata/io/base.py
pysuricata/render/__init__.py
pysuricata/render/boolean_card.py
pysuricata/render/card_base.py
pysuricata/render/card_config.py
pysuricata/render/card_factory.py
pysuricata/render/card_types.py
pysuricata/render/cards.py
pysuricata/render/cards_new.py
pysuricata/render/categorical_card.py
pysuricata/render/datetime_card.py
pysuricata/render/format_utils.py
pysuricata/render/histogram_svg.py
pysuricata/render/html.py
pysuricata/render/markdown_utils.py
pysuricata/render/missing_columns.py
pysuricata-0.0.11.dist-info/licenses/LICENSE
pysuricata-0.0.11.dist-info/METADATA
pysuricata-0.0.11.dist-info/WHEEL
pysuricata-0.0.11.dist-info/top_level.txt
pysuricata-0.0.11.dist-info/RECORD
