Metadata-Version: 2.4
Name: pysuricata
Version: 0.0.11
Summary: A lightweight EDA tool inspired by the curious nature of suricates. Built just for fun 🔬.
Author-email: Alvaro Diez <alvarodiez20@gmail.com>
License-Expression: MIT
Project-URL: Repository, https://github.com/alvarodiez20/pysuricata
Classifier: Development Status :: 4 - Beta
Classifier: Intended Audience :: Developers
Classifier: Operating System :: OS Independent
Classifier: Programming Language :: Python :: 3.9
Classifier: Programming Language :: Python :: 3.10
Classifier: Programming Language :: Python :: 3.11
Classifier: Programming Language :: Python :: 3.12
Classifier: Programming Language :: Python :: 3.13
Classifier: Programming Language :: Python :: Implementation :: CPython
Requires-Python: <3.14,>=3.9
License-File: LICENSE
Requires-Dist: pandas~=2.0; python_version < "3.13"
Requires-Dist: pandas<3.0,>=2.2.3; python_version >= "3.13"
Requires-Dist: numpy>=2.1; python_version >= "3.13"
Requires-Dist: markdown>=3.4.0
Provides-Extra: polars
Requires-Dist: polars<2.0,>=1.0; extra == "polars"
Dynamic: license-file
